felafax/__init__.py
felafax/config.py
felafax/cli/__init__.py
felafax/cli/args.py
felafax/cli/common.py
felafax/cli/log.py
felafax/cli/main.py
felafax/cli/commands/__init__.py
felafax/cli/commands/accelerator.py
felafax/cli/commands/auth.py
felafax/cli/commands/files.py
felafax/cli/commands/model.py
felafax/cli/commands/tune.py
felafax/core/__init__.py
felafax/core/constants.py
felafax/core/storage/__init__.py
felafax/core/storage/base.py
felafax/core/storage/gcs.py
felafax/server/__init__.py
felafax/server/common.py
felafax/server/main.py
felafax/server/api/__init__.py
felafax/server/api/accelerators.py
felafax/server/api/auth.py
felafax/server/api/billing.py
felafax/server/api/dataset.py
felafax/server/api/finetune.py
felafax/server/api/models.py
felafax/server/handlers/__init__.py
felafax/server/handlers/accelerator.py
felafax/server/handlers/base.py
felafax/server/handlers/dataset.py
felafax/server/handlers/finetune.py
felafax/server/handlers/indexes.py
felafax/server/handlers/job.py
felafax/server/handlers/model.py
felafax/server/handlers/user.py
felafax/server/models/__init__.py
felafax/server/models/accelerator.py
felafax/server/models/billing.py
felafax/server/models/dataset.py
felafax/server/models/finetune.py
felafax/server/models/indexes.py
felafax/server/models/job.py
felafax/server/models/model.py
felafax/server/models/user.py
felafax_cli-0.1.16.dist-info/LICENSE
felafax_cli-0.1.16.dist-info/METADATA
felafax_cli-0.1.16.dist-info/WHEEL
felafax_cli-0.1.16.dist-info/entry_points.txt
felafax_cli-0.1.16.dist-info/top_level.txt
felafax_cli-0.1.16.dist-info/RECORD
