Metadata-Version: 2.1
Name: felafax-cli
Version: 0.1.16
Summary: CLI tool for interacting with the Felafax platform; fine-tuning and inference on non-NVIDIA chipsets.
Author: Nikhil Sonti
Author-email: nikhil@felafax.ai
Classifier: Development Status :: 3 - Alpha
Classifier: Intended Audience :: Developers
Classifier: License :: OSI Approved :: MIT License
Classifier: Programming Language :: Python :: 3
Classifier: Programming Language :: Python :: 3.8
Classifier: Programming Language :: Python :: 3.9
Requires-Python: >=3.8
License-File: LICENSE
Requires-Dist: typer
Requires-Dist: httpx
Requires-Dist: pyyaml
Requires-Dist: pathlib
Requires-Dist: pydantic
Requires-Dist: pydantic-settings
Requires-Dist: requests
Requires-Dist: python-multipart
Requires-Dist: colorlog
Requires-Dist: posthog
